{"assets":[],"ddd":0,"fr":30,"h":50,"ip":0,"layers":[{"ddd":0,"ind":1,"ty":4,"nm":"오귀","hd":false,"sr":1,"ks":{"a":{"a":0,"k":[30.908,13.224]},"o":{"a":0,"k":100},"p":{"a":1,"k":[{"t":0,"s":[31.046,17.415],"i":{"x":0.75,"y":0.75},"o":{"x":0.25,"y":0.25},"ti":[0,0],"to":[0,0]},{"t":7.5,"s":[31.046,14.415],"i":{"x":0.75,"y":0.75},"o":{"x":0.25,"y":0.25},"ti":[0,0],"to":[0,0]},{"t":15,"s":[31.046,17.415],"i":{"x":0,"y":0},"o":{"x":1,"y":1}}]},"r":{"a":1,"k":[{"t":0,"s":[0],"i":{"x":0.75,"y":0.75},"o":{"x":0.25,"y":0.25}},{"t":7.5,"s":[12],"i":{"x":0.75,"y":0.75},"o":{"x":0.25,"y":0.25}},{"t":15,"s":[0],"i":{"x":0,"y":0},"o":{"x":1,"y":1}}]},"s":{"a":0,"k":[100,100]},"sk":{"a":0,"k":0},"sa":{"a":0,"k":0}},"ao":0,"ip":0,"op":16,"st":0,"bm":0,"shapes":[{"ty":"sh","hd":false,"nm":"오귀","d":1,"ks":{"a":0,"k":{"c":false,"i":[[0,0],[-3.552,-2.77],[-0.431,-1.704],[1.132,-1.165],[1.598,-0.293],[2.678,2.536],[-0.471,3.659]],"o":[[3.558,2.77],[1.39,1.085],[0.397,1.572],[-1.132,1.164],[-3.632,0.67],[-2.678,-2.536],[0,0]],"v":[[35.18,12.139],[45.848,20.456],[49.141,24.455],[47.779,28.912],[43.474,31.029],[33.238,28.011],[29.651,17.973]]}}},{"ty":"st","hd":false,"bm":0,"c":{"a":0,"k":[0.812,0.435,0.361]},"lc":2,"lj":2,"ml":4,"o":{"a":0,"k":100},"w":{"a":0,"k":2}}]},{"ddd":0,"ind":2,"ty":4,"nm":"코","hd":false,"sr":1,"ks":{"a":{"a":0,"k":[11.989,16.301]},"o":{"a":0,"k":100},"p":{"a":1,"k":[{"t":0,"s":[12.127,20.492],"i":{"x":0.75,"y":0.75},"o":{"x":0.25,"y":0.25},"ti":[0,0],"to":[0,0]},{"t":7.5,"s":[12.127,17.492],"i":{"x":0.75,"y":0.75},"o":{"x":0.25,"y":0.25},"ti":[0,0],"to":[0,0]},{"t":15,"s":[12.127,20.492],"i":{"x":0,"y":0},"o":{"x":1,"y":1}}]},"r":{"a":0,"k":0},"s":{"a":0,"k":[100,100]},"sk":{"a":0,"k":0},"sa":{"a":0,"k":0}},"ao":0,"ip":0,"op":16,"st":0,"bm":0,"shapes":[{"ty":"sh","hd":false,"nm":"코","d":1,"ks":{"a":0,"k":{"c":false,"i":[[0,0],[0,0]],"o":[[0,0],[0,0]],"v":[[16.018,23.26],[15.944,26.129]]}}},{"ty":"sh","hd":false,"nm":"코","d":1,"ks":{"a":0,"k":{"c":false,"i":[[0,0],[1.314,0],[0,0.704],[-1.314,0],[0,-0.703]],"o":[[0,0.704],[-1.314,0],[0,-0.703],[1.314,0],[0,0]],"v":[[18.61,21.396],[16.231,22.67],[13.851,21.396],[16.231,20.123],[18.611,21.396]]}}},{"ty":"sh","hd":false,"nm":"코","d":1,"ks":{"a":0,"k":{"c":false,"i":[[0,0],[0,0]],"o":[[0,0],[0,0]],"v":[[16.018,23.26],[15.944,26.129]]}}},{"ty":"sh","hd":false,"nm":"코","d":1,"ks":{"a":0,"k":{"c":false,"i":[[0,0],[1.314,0],[0,0.704],[-1.314,0],[0,-0.703]],"o":[[0,0.704],[-1.314,0],[0,-0.703],[1.314,0],[0,0]],"v":[[18.61,21.396],[16.231,22.67],[13.851,21.396],[16.231,20.123],[18.611,21.396]]}}},{"ty":"sh","hd":false,"nm":"코","d":1,"ks":{"a":0,"k":{"c":false,"i":[[0,0],[0,0]],"o":[[0,0],[0,0]],"v":[[16.018,23.26],[15.944,26.129]]}}},{"ty":"sh","hd":false,"nm":"코","d":1,"ks":{"a":0,"k":{"c":false,"i":[[0,0],[1.314,0],[0,0.704],[-1.314,0],[0,-0.703]],"o":[[0,0.704],[-1.314,0],[0,-0.703],[1.314,0],[0,0]],"v":[[18.61,21.396],[16.231,22.67],[13.851,21.396],[16.231,20.123],[18.611,21.396]]}}},{"ty":"st","hd":false,"bm":0,"c":{"a":0,"k":[0.812,0.435,0.361]},"lc":2,"lj":2,"ml":4,"o":{"a":0,"k":100},"w":{"a":0,"k":2}}]},{"ddd":0,"ind":3,"ty":4,"nm":"눙","hd":false,"sr":1,"ks":{"a":{"a":0,"k":[0,0]},"o":{"a":0,"k":100},"p":{"a":1,"k":[{"t":0,"s":[0.138,4.191],"i":{"x":0.75,"y":0.75},"o":{"x":0.25,"y":0.25},"ti":[0,0],"to":[0,0]},{"t":7.5,"s":[0.138,1.191],"i":{"x":0.75,"y":0.75},"o":{"x":0.25,"y":0.25},"ti":[0,0],"to":[0,0]},{"t":15,"s":[0.138,4.191],"i":{"x":0,"y":0},"o":{"x":1,"y":1}}]},"r":{"a":0,"k":0},"s":{"a":0,"k":[100,100]},"sk":{"a":0,"k":0},"sa":{"a":0,"k":0}},"ao":0,"ip":0,"op":16,"st":0,"bm":0,"shapes":[{"ty":"sh","hd":false,"nm":"눙","d":1,"ks":{"a":0,"k":{"c":false,"i":[[0,0],[0,0.631],[0.587,0],[0,-0.631],[-0.587,0]],"o":[[0.587,0],[0,-0.63],[-0.588,0],[0,0.631],[0,0]],"v":[[14.053,18.655],[15.116,17.514],[14.053,16.372],[12.989,17.514],[14.052,18.655]]}}},{"ty":"sh","hd":false,"nm":"눙","d":1,"ks":{"a":0,"k":{"c":false,"i":[[0,0],[0,0.631],[0.587,0],[0,-0.631],[-0.587,0]],"o":[[0.587,0],[0,-0.63],[-0.587,0],[0,0.631],[0,0]],"v":[[19.576,18.655],[20.639,17.514],[19.576,16.372],[18.513,17.514],[19.576,18.655]]}}},{"ty":"fl","hd":false,"bm":0,"c":{"a":0,"k":[0.812,0.435,0.361]},"r":1,"o":{"a":0,"k":100}}]},{"ddd":0,"ind":4,"ty":4,"nm":"몸","hd":false,"sr":1,"ks":{"a":{"a":0,"k":[0,0]},"o":{"a":0,"k":100},"p":{"a":1,"k":[{"t":0,"s":[0.138,4.191],"i":{"x":0.75,"y":0.75},"o":{"x":0.25,"y":0.25},"ti":[0,0],"to":[0,0]},{"t":7.5,"s":[0.138,1.191],"i":{"x":0.75,"y":0.75},"o":{"x":0.25,"y":0.25},"ti":[0,0],"to":[0,0]},{"t":15,"s":[0.138,4.191],"i":{"x":0,"y":0},"o":{"x":1,"y":1}}]},"r":{"a":0,"k":0},"s":{"a":0,"k":[100,100]},"sk":{"a":0,"k":0},"sa":{"a":0,"k":0}},"ao":0,"ip":0,"op":16,"st":0,"bm":0,"shapes":[{"ty":"sh","hd":false,"nm":"몸","d":1,"ks":{"a":0,"k":{"c":false,"i":[[0,0],[3.357,-4.624],[-2.707,-5.14],[-6.339,-0.821],[0,0],[-5.874,4.399],[3.178,7.394],[7.351,-0.132],[8.34,1.968]],"o":[[-8.104,-1.91],[-3.357,4.624],[3.27,6.207],[0,0],[6.995,0.907],[6.053,-4.532],[-3.449,-8.043],[-8.414,0.15],[0,0]],"v":[[27.1,3.745],[11.093,8.891],[9.236,25.607],[26.082,34.08],[40.52,35.955],[61.05,33.208],[66.304,11.421],[49.124,0.814],[27.1,3.745]]}}},{"ty":"gf","hd":false,"bm":0,"e":{"a":0,"k":[37.73200036069632,54.24804137517664]},"g":{"p":2,"k":{"a":0,"k":[0,0.945,0.812,0.729,1,0.929,0.863,0.824,0,1,1,1]}},"t":2,"a":{"a":0,"k":0},"h":{"a":0,"k":0},"o":{"a":0,"k":100},"r":1,"s":{"a":0,"k":[37.73200036069632,18.732588574190327]}}]},{"ddd":0,"ind":5,"ty":4,"nm":"왼귀","hd":false,"sr":1,"ks":{"a":{"a":0,"k":[11.08,17.394]},"o":{"a":0,"k":100},"p":{"a":1,"k":[{"t":0,"s":[11.218,21.584],"i":{"x":0.75,"y":0.75},"o":{"x":0.25,"y":0.25},"ti":[0,0],"to":[0,0]},{"t":7.5,"s":[12.218,18.584],"i":{"x":0.75,"y":0.75},"o":{"x":0.25,"y":0.25},"ti":[0,0],"to":[0,0]},{"t":15,"s":[11.218,21.584],"i":{"x":0,"y":0},"o":{"x":1,"y":1}}]},"r":{"a":1,"k":[{"t":0,"s":[0],"i":{"x":0.75,"y":0.75},"o":{"x":0.25,"y":0.25}},{"t":7.5,"s":[-19],"i":{"x":0.75,"y":0.75},"o":{"x":0.25,"y":0.25}},{"t":15,"s":[0],"i":{"x":0,"y":0},"o":{"x":1,"y":1}}]},"s":{"a":0,"k":[100,100]},"sk":{"a":0,"k":0},"sa":{"a":0,"k":0}},"ao":0,"ip":0,"op":16,"st":0,"bm":0,"shapes":[{"ty":"sh","hd":false,"nm":"왼귀","d":1,"ks":{"a":0,"k":{"c":false,"i":[[0,0],[1.27,-2.163],[-1.575,-1.95],[-2.063,1.417]],"o":[[-2.488,0.31],[-1.27,2.162],[1.575,1.95],[0,0]],"v":[[8.345,14.071],[2.759,17.961],[3.109,25.016],[9.351,26.198]]}}},{"ty":"st","hd":false,"bm":0,"c":{"a":0,"k":[0.812,0.435,0.361]},"lc":2,"lj":2,"ml":4,"o":{"a":0,"k":100},"w":{"a":0,"k":2}}]},{"ddd":0,"ind":6,"ty":4,"nm":"꼬리","hd":false,"sr":1,"ks":{"a":{"a":0,"k":[65.643,25.733]},"o":{"a":0,"k":100},"p":{"a":1,"k":[{"t":0,"s":[65.781,29.924],"i":{"x":0.75,"y":0.75},"o":{"x":0.25,"y":0.25},"ti":[0,0],"to":[0,0]},{"t":7.5,"s":[65.781,26.924],"i":{"x":0.75,"y":0.75},"o":{"x":0.25,"y":0.25},"ti":[0,0],"to":[0,0]},{"t":15,"s":[65.781,29.924],"i":{"x":0,"y":0},"o":{"x":1,"y":1}}]},"r":{"a":1,"k":[{"t":0,"s":[0],"i":{"x":0.75,"y":0.75},"o":{"x":0.25,"y":0.25}},{"t":7.5,"s":[20],"i":{"x":0.75,"y":0.75},"o":{"x":0.25,"y":0.25}},{"t":15,"s":[0],"i":{"x":0,"y":0},"o":{"x":1,"y":1}}]},"s":{"a":0,"k":[100,100]},"sk":{"a":0,"k":0},"sa":{"a":0,"k":0}},"ao":0,"ip":0,"op":16,"st":0,"bm":0,"shapes":[{"ty":"sh","hd":false,"nm":"꼬리","d":1,"ks":{"a":0,"k":{"c":false,"i":[[0,0],[-2.667,2.868],[-1.632,3.562],[1.385,-3.516],[3.672,-0.901],[2.051,1.157]],"o":[[3.892,0.533],[2.667,-2.869],[0.127,3.775],[-1.385,3.516],[-2.289,0.553],[0,0]],"v":[[64.86,24.122],[74.827,19.814],[80.804,9.746],[79.408,20.909],[71.534,28.464],[64.78,27.524]]}}},{"ty":"gf","hd":false,"bm":0,"e":{"a":0,"k":[72.81000051945364,27.01626047195976]},"g":{"p":2,"k":{"a":0,"k":[0,0.902,0.651,0.502,1,0.863,0.714,0.624,0,1,1,1]}},"t":2,"a":{"a":0,"k":0},"h":{"a":0,"k":0},"o":{"a":0,"k":100},"r":1,"s":{"a":0,"k":[72.81000051945364,19.23500012222626]}}]},{"ddd":0,"ind":7,"ty":4,"nm":"오발","hd":false,"sr":1,"ks":{"a":{"a":1,"k":[{"t":0,"s":[51.943,34.43],"i":{"x":0.75,"y":0.75},"o":{"x":0.25,"y":0.25}},{"t":7.5,"s":[51.943,44.086],"i":{"x":0.75,"y":0.75},"o":{"x":0.25,"y":0.25}},{"t":15,"s":[51.943,34.447],"i":{"x":0,"y":0},"o":{"x":1,"y":1}}]},"o":{"a":0,"k":100},"p":{"a":1,"k":[{"t":0,"s":[52.081,38.621],"i":{"x":0.75,"y":0.75},"o":{"x":0.25,"y":0.25},"ti":[0,0],"to":[0,0]},{"t":7.5,"s":[51.593,33.919],"i":{"x":0.75,"y":0.75},"o":{"x":0.25,"y":0.25},"ti":[0,0],"to":[0,0]},{"t":15,"s":[52.081,38.691],"i":{"x":0,"y":0},"o":{"x":1,"y":1}}]},"r":{"a":1,"k":[{"t":0,"s":[0],"i":{"x":0.75,"y":0.75},"o":{"x":0.25,"y":0.25}},{"t":7.5,"s":[-16],"i":{"x":0.75,"y":0.75},"o":{"x":0.25,"y":0.25}},{"t":15,"s":[0],"i":{"x":0,"y":0},"o":{"x":1,"y":1}}]},"s":{"a":0,"k":[100,100]},"sk":{"a":0,"k":0},"sa":{"a":0,"k":0}},"ao":0,"ip":0,"op":16,"st":0,"bm":0,"shapes":[{"ty":"sh","hd":false,"nm":"오발","d":1,"ks":{"a":1,"k":[{"t":0,"s":[{"c":false,"i":[[0,0],[0.045,-0.505],[-0.603,-0.603],[-1.161,-0.006],[0,0],[-0.978,0.809],[0.029,1.107],[0.093,0.743]],"o":[[-0.108,0.496],[-0.074,0.854],[0.817,0.82],[0,0],[1.27,0],[0.85,-0.706],[-0.026,-0.748],[0,0]],"v":[[46.29,35.985],[46.06,37.488],[46.79,39.863],[50.061,40.74],[53.808,40.74],[57.447,39.897],[58.625,36.92],[58.447,34.683]]}],"i":{"x":0.75,"y":0.75},"o":{"x":0.25,"y":0.25}},{"t":7.5,"s":[{"c":false,"i":[[0,0],[0.045,-0.647],[-0.603,-0.772],[-1.161,-0.008],[0,0],[-0.978,1.036],[0.029,1.417],[0.093,0.951]],"o":[[-0.108,0.635],[-0.074,1.094],[0.817,1.05],[0,0],[1.27,0],[0.85,-0.904],[-0.026,-0.958],[0,0]],"v":[[46.29,46.077],[46.06,48.002],[46.79,51.043],[50.061,52.166],[53.808,52.166],[57.447,51.086],[58.625,47.275],[58.447,44.41]]}],"i":{"x":0.75,"y":0.75},"o":{"x":0.25,"y":0.25}},{"t":15,"s":[{"c":false,"i":[[0,0],[0.045,-0.506],[-0.603,-0.603],[-1.161,-0.006],[0,0],[-0.978,0.809],[0.029,1.108],[0.093,0.743]],"o":[[-0.108,0.496],[-0.074,0.854],[0.817,0.82],[0,0],[1.27,0],[0.85,-0.706],[-0.026,-0.748],[0,0]],"v":[[46.29,36.003],[46.06,37.507],[46.79,39.883],[50.061,40.76],[53.808,40.76],[57.447,39.917],[58.625,36.938],[58.447,34.7]]}],"i":{"x":0,"y":0},"o":{"x":1,"y":1}}]}},{"ty":"gf","hd":false,"bm":0,"e":{"a":0,"k":[52.33600005002073,46.652521338759286]},"g":{"p":2,"k":{"a":0,"k":[0,0.902,0.651,0.502,1,0.863,0.714,0.624,0,1,1,1]}},"t":2,"a":{"a":0,"k":0},"h":{"a":0,"k":0},"o":{"a":0,"k":100},"r":1,"s":{"a":0,"k":[52.33600005002073,37.71099998844938]}}]},{"ddd":0,"ind":8,"ty":4,"nm":"왼발","hd":false,"sr":1,"ks":{"a":{"a":1,"k":[{"t":0,"s":[37.17,33.596],"i":{"x":0.75,"y":0.75},"o":{"x":0.25,"y":0.25}},{"t":7.5,"s":[37.17,43.916],"i":{"x":0.75,"y":0.75},"o":{"x":0.25,"y":0.25}},{"t":15,"s":[37.17,33.591],"i":{"x":0,"y":0},"o":{"x":1,"y":1}}]},"o":{"a":0,"k":100},"p":{"a":1,"k":[{"t":0,"s":[37.308,37.787],"i":{"x":0.75,"y":0.75},"o":{"x":0.25,"y":0.25},"ti":[0,0],"to":[0,0]},{"t":7.5,"s":[38.01,32.626],"i":{"x":0.75,"y":0.75},"o":{"x":0.25,"y":0.25},"ti":[0,0],"to":[0,0]},{"t":15,"s":[37.308,37.843],"i":{"x":0,"y":0},"o":{"x":1,"y":1}}]},"r":{"a":1,"k":[{"t":0,"s":[0],"i":{"x":0.75,"y":0.75},"o":{"x":0.25,"y":0.25}},{"t":7.5,"s":[18],"i":{"x":0.75,"y":0.75},"o":{"x":0.25,"y":0.25}},{"t":15,"s":[0],"i":{"x":0,"y":0},"o":{"x":1,"y":1}}]},"s":{"a":0,"k":[100,100]},"sk":{"a":0,"k":0},"sa":{"a":0,"k":0}},"ao":0,"ip":0,"op":16,"st":0,"bm":0,"shapes":[{"ty":"sh","hd":false,"nm":"왼발","d":1,"ks":{"a":1,"k":[{"t":0,"s":[{"c":false,"i":[[0,0],[0.075,-0.854],[-0.603,-0.602],[-1.16,-0.006],[0,0],[-0.977,0.809],[0.029,1.107],[0.11,0.457]],"o":[[-0.316,0.798],[-0.075,0.854],[0.817,0.82],[0,0],[1.27,0],[0.85,-0.706],[-0.016,-0.47],[0,0]],"v":[[31.767,33.781],[30.473,37.739],[31.203,40.114],[34.473,40.992],[38.221,40.992],[41.859,40.149],[43.037,37.172],[42.847,35.778]]}],"i":{"x":0.75,"y":0.75},"o":{"x":0.25,"y":0.25}},{"t":7.5,"s":[{"c":false,"i":[[0,0],[0.075,-1.116],[-0.603,-0.787],[-1.16,-0.008],[0,0],[-0.977,1.057],[0.029,1.447],[0.11,0.598]],"o":[[-0.316,1.043],[-0.075,1.116],[0.817,1.072],[0,0],[1.27,0],[0.85,-0.923],[-0.016,-0.614],[0,0]],"v":[[31.767,44.157],[30.473,49.331],[31.203,52.436],[34.473,53.583],[38.221,53.583],[41.859,52.481],[43.037,48.59],[42.847,46.768]]}],"i":{"x":0.75,"y":0.75},"o":{"x":0.25,"y":0.25}},{"t":15,"s":[{"c":false,"i":[[0,0],[0.075,-0.854],[-0.603,-0.602],[-1.16,-0.006],[0,0],[-0.977,0.809],[0.029,1.107],[0.11,0.457]],"o":[[-0.316,0.798],[-0.075,0.854],[0.817,0.82],[0,0],[1.27,0],[0.85,-0.706],[-0.016,-0.47],[0,0]],"v":[[31.767,33.776],[30.473,37.734],[31.203,40.108],[34.473,40.986],[38.221,40.986],[41.859,40.143],[43.037,37.167],[42.847,35.773]]}],"i":{"x":0,"y":0},"o":{"x":1,"y":1}}]}},{"ty":"gf","hd":false,"bm":0,"e":{"a":0,"k":[36.7490003780802,45.08786008614602]},"g":{"p":2,"k":{"a":0,"k":[0,0.902,0.651,0.502,1,0.863,0.714,0.624,0,1,1,1]}},"t":2,"a":{"a":0,"k":0},"h":{"a":0,"k":0},"o":{"a":0,"k":100},"r":1,"s":{"a":0,"k":[36.7490003780802,37.38700041105362]}}]},{"ddd":0,"ind":9,"ty":4,"nm":"Layer 2","hd":false,"sr":1,"ks":{"a":{"a":0,"k":[41.31,41.03]},"o":{"a":0,"k":100},"p":{"a":0,"k":[41.448,45.221]},"r":{"a":0,"k":0},"s":{"a":0,"k":[100,100]},"sk":{"a":0,"k":0},"sa":{"a":0,"k":0}},"ao":0,"ip":0,"op":16,"st":0,"bm":1,"shapes":[{"ty":"gr","hd":false,"nm":"Path 1 Group","bm":0,"it":[{"ty":"sh","hd":false,"nm":"Path 1","d":1,"ks":{"a":0,"k":{"c":true,"i":[[0,0],[17.121,0],[0,1.657],[-17.121,0],[0,-1.657]],"o":[[0,1.657],[-17.121,0],[0,-1.657],[17.121,0],[0,0]],"v":[[72,41],[41,44],[10,41],[41,38],[72,41]]}}},{"ty":"fl","hd":false,"bm":0,"c":{"a":0,"k":[0.435,0.522,0.702]},"r":1,"o":{"a":0,"k":100}},{"ty":"tr","nm":"Transform","a":{"a":0,"k":[0,0]},"o":{"a":0,"k":100},"p":{"a":0,"k":[0,0]},"r":{"a":0,"k":0},"s":{"a":0,"k":[100,100]},"sk":{"a":0,"k":0},"sa":{"a":0,"k":0}}],"np":0}]},{"ddd":0,"ind":11,"ty":4,"nm":"Screen","hd":false,"sr":1,"ks":{"a":{"a":0,"k":[43,25]},"o":{"a":0,"k":100},"p":{"a":0,"k":[43,25]},"r":{"a":0,"k":0},"s":{"a":0,"k":[100,100]},"sk":{"a":0,"k":0},"sa":{"a":0,"k":0}},"ao":0,"ip":0,"op":16,"st":0,"bm":0,"shapes":[{"ty":"gr","hd":false,"nm":"Screen Group","bm":0,"it":[{"ty":"rc","hd":false,"nm":"Screen","d":1,"p":{"a":0,"k":[43,25]},"r":{"a":0,"k":0},"s":{"a":0,"k":[86,50]}},{"ty":"fl","hd":false,"bm":0,"c":{"a":0,"k":[1,1,1]},"r":1,"o":{"a":0,"k":0}},{"ty":"tr","nm":"Transform","a":{"a":0,"k":[0,0]},"o":{"a":0,"k":100},"p":{"a":0,"k":[0,0]},"r":{"a":0,"k":0},"s":{"a":0,"k":[100,100]},"sk":{"a":0,"k":0},"sa":{"a":0,"k":0}}],"np":0}]}],"meta":{"g":"@phase-software/lottie-exporter 0.7.0"},"nm":"","op":15,"v":"5.6.0","w":86}